MANIFEST.in
README.md
setup.py
chicago/__init__.py
chicago/base.py
chicago/community_areas.py
chicago/neighborhoods.py
chicago/precincts.py
chicago/tracts.py
chicago/version.py
chicago/zip_codes.py
chicago.egg-info/PKG-INFO
chicago.egg-info/SOURCES.txt
chicago.egg-info/dependency_links.txt
chicago.egg-info/top_level.txt
chicago/cook_suburbs/__init__.py
chicago/cook_suburbs/precincts.py
chicago/data/CommAreas.csv
chicago/data/Neighborhoods_2012b.csv
chicago/data/census_tracts_as_of_2010.geojson
chicago/data/chicago_precinct_census_tract_crosswalk.csv
chicago/data/chicago_zip_codes.geojson
chicago/data/cook_suburban_precincts_as_of_2016.csv
chicago/data/county_fips.csv
chicago/data/suburban_cook_precinct_census_tract_crosswalk.csv
chicago/illinois/__init__.py
chicago/illinois/counties.py