Metadata-Version: 1.1
Name: chicago
Version: 0.4.1
Summary: Chicago meta information and other fun stuff
Home-page: https://github.com/newsapps/python-chicago
Author: Geoff Hing for the Chicago Tribune News Applications Team
Author-email: geoffhing@gmail.com
License: UNKNOWN
Keywords: chicago,geography,city
Platform: UNKNOWN
Classifier: Development Status :: 3 - Alpha
Classifier: License :: OSI Approved :: MIT License
Classifier: Operating System :: OS Independent
Classifier: Programming Language :: Python
